{
    "simulations": [
        {
            "gOff": 7.723066346443375e-07,
            "gOn": 2.730684400376049e-06,
            "kV": 0.5,
            "modelSize": "tiny",
            "optimiser": "adam",
            "doubleWeights": true,
            "discretisation": false,
            "conductanceDrifting": true,
            "number_conductance_levels": 10,
            "excluded_weights_proportion": 0.015,
            "numberHiddenLayers": 1,
            "nonidealities": [
                {
                    "type": "StuckAtValue",
                    "parameters": [
                        2.730684400376049e-06
                    ]
                }
            ],
            "noiseVariance": 0.0,
            "numberSimulations": 1
        },
        {
            "gOff": 7.723066346443375e-07,
            "gOn": 2.730684400376049e-06,
            "kV": 0.5,
            "modelSize": "tiny",
            "optimiser": "adam",
            "doubleWeights": true,
            "discretisation": false,
            "conductanceDrifting": true,
            "number_conductance_levels": 10,
            "excluded_weights_proportion": 0.015,
            "numberHiddenLayers": 1,
            "nonidealities": [
                {
                    "type": "StuckAtValue",
                    "parameters": [
                        2.730684400376049e-06
                    ]
                }
            ],
            "noiseVariance": 0.1,
            "numberSimulations": 1
        },
        {
            "gOff": 7.723066346443375e-07,
            "gOn": 2.730684400376049e-06,
            "kV": 0.5,
            "modelSize": "tiny",
            "optimiser": "adam",
            "doubleWeights": true,
            "discretisation": false,
            "conductanceDrifting": true,
            "number_conductance_levels": 10,
            "excluded_weights_proportion": 0.015,
            "numberHiddenLayers": 1,
            "nonidealities": [
                {
                    "type": "StuckAtValue",
                    "parameters": [
                        2.730684400376049e-06
                    ]
                }
            ],
            "noiseVariance": 0.25,
            "numberSimulations": 1
        },
        {
            "gOff": 7.723066346443375e-07,
            "gOn": 2.730684400376049e-06,
            "kV": 0.5,
            "modelSize": "tiny",
            "optimiser": "adam",
            "doubleWeights": true,
            "discretisation": false,
            "conductanceDrifting": true,
            "number_conductance_levels": 10,
            "excluded_weights_proportion": 0.015,
            "numberHiddenLayers": 1,
            "nonidealities": [
                {
                    "type": "StuckAtValue",
                    "parameters": [
                        2.730684400376049e-06
                    ]
                }
            ],
            "noiseVariance": 0.5,
            "numberSimulations": 1
        },
        {
            "gOff": 7.723066346443375e-07,
            "gOn": 2.730684400376049e-06,
            "kV": 0.5,
            "modelSize": "tiny",
            "optimiser": "adam",
            "doubleWeights": true,
            "discretisation": false,
            "conductanceDrifting": true,
            "number_conductance_levels": 10,
            "excluded_weights_proportion": 0.015,
            "numberHiddenLayers": 1,
            "nonidealities": [
                {
                    "type": "StuckAtValue",
                    "parameters": [
                        2.730684400376049e-06
                    ]
                }
            ],
            "noiseVariance": 0.75,
            "numberSimulations": 1
        }
    ]
}
